{"first": "Lisa", "last": "McClain", "filed": "11/21/2025", "state_dst": "MI09", "chamber": "House", "txns": [{"date": "2025-10-31", "owner": "", "symbol": "BP", "asset": "Charles Schwab 401K > Schwab 893 SP BP p.l.c. Common Stock", "side": "SELL", "lo": 1001, "hi": 15000}, {"date": "2025-10-30", "owner": "", "symbol": "BP", "asset": "Charles Schwab 401K > Schwab 893 SP BP p.l.c. Common Stock", "side": "BUY", "lo": 1001, "hi": 15000}, {"date": "2025-10-30", "owner": "", "symbol": "BP", "asset": "Charles Schwab 401K > Schwab 893 SP BP p.l.c. Common Stock", "side": "SELL", "lo": 1001, "hi": 15000}, {"date": "2025-10-30", "owner": "", "symbol": "BCO", "asset": "Charles Schwab Brokerage Account 924 SP Brinks Company", "side": "SELL", "lo": 1001, "hi": 15000}, {"date": "2025-10-30", "owner": "", "symbol": "BCO", "asset": "Charles Schwab Brokerage Account 924 SP Brinks Company", "side": "BUY", "lo": 1001, "hi": 15000}, {"date": "2025-10-31", "owner": "", "symbol": "BCO", "asset": "Charles Schwab 401K > Schwab 893 SP Brinks Company", "side": "SELL", "lo": 1001, "hi": 15000}, {"date": "2025-10-31", "owner": "", "symbol": "CIEN", "asset": "Charles Schwab 401K > Schwab 893 SP Ciena Corporation", "side": "SELL", "lo": 1001, "hi": 15000}, {"date": "2025-10-15", "owner": "", "symbol": "CIEN", "asset": "Charles Schwab 401K > Schwab 893 SP Ciena Corporation", "side": "SELL", "lo": 1001, "hi": 15000}, {"date": "2025-10-30", "owner": "", "symbol": "CIEN", "asset": "Charles Schwab Brokerage Account 924 SP Ciena Corporation", "side": "BUY", "lo": 1001, "hi": 15000}, {"date": "2025-10-30", "owner": "", "symbol": "CIEN", "asset": "Charles Schwab 401K > Schwab 893 SP Ciena Corporation", "side": "SELL", "lo": 1001, "hi": 15000}, {"date": "2025-10-30", "owner": "", "symbol": "CLX", "asset": "Charles Schwab Brokerage Account 924 SP Clorox Company", "side": "SELL", "lo": 1001, "hi": 15000}, {"date": "2025-10-30", "owner": "", "symbol": "CLX", "asset": "Charles Schwab Brokerage Account 924 SP Clorox Company", "side": "BUY", "lo": 1001, "hi": 15000}, {"date": "2025-10-31", "owner": "", "symbol": "CLX", "asset": "Charles Schwab 401K > Schwab 893 SP Clorox Company", "side": "SELL", "lo": 1001, "hi": 15000}, {"date": "2025-10-31", "owner": "", "symbol": "KO", "asset": "Charles Schwab 401K > Schwab 893 SP Coca-Cola Company", "side": "SELL", "lo": 1001, "hi": 15000}, {"date": "2025-10-30", "owner": "", "symbol": "KO", "asset": "Charles Schwab 401K > Schwab 893 SP Coca-Cola Company", "side": "SELL", "lo": 1001, "hi": 15000}, {"date": "2025-10-30", "owner": "", "symbol": "KO", "asset": "Charles Schwab Brokerage Account 924 SP Coca-Cola Company", "side": "BUY", "lo": 1001, "hi": 15000}, {"date": "2025-10-30", "owner": "", "symbol": "COHR", "asset": "Charles Schwab 401K > Schwab 893 SP Coherent Corp.", "side": "BUY", "lo": 1001, "hi": 15000}, {"date": "2025-10-30", "owner": "", "symbol": "COHR", "asset": "Charles Schwab 401K > Schwab 893 SP Coherent Corp.", "side": "SELL", "lo": 1001, "hi": 15000}, {"date": "2025-10-31", "owner": "", "symbol": "COHR", "asset": "Charles Schwab Brokerage Account 924 SP Coherent Corp.", "side": "SELL", "lo": 1001, "hi": 15000}, {"date": "2025-10-31", "owner": "", "symbol": "DUK", "asset": "Charles Schwab 401K > Schwab 893 SP Duke Energy Corporation", "side": "SELL", "lo": 1001, "hi": 15000}, {"date": "2025-10-30", "owner": "", "symbol": "DUK", "asset": "Charles Schwab 401K > Schwab 893 SP Duke Energy Corporation", "side": "SELL", "lo": 1001, "hi": 15000}, {"date": "2025-10-30", "owner": "", "symbol": "DUK", "asset": "Charles Schwab Brokerage Account 924 SP Duke Energy Corporation", "side": "BUY", "lo": 1001, "hi": 15000}, {"date": "2025-10-31", "owner": "", "symbol": "EXC", "asset": "Charles Schwab 401K > Schwab 893 SP Exelon Corporation", "side": "SELL", "lo": 1001, "hi": 15000}, {"date": "2025-10-30", "owner": "", "symbol": "EXC", "asset": "Charles Schwab 401K > Schwab 893 SP Exelon Corporation", "side": "SELL", "lo": 1001, "hi": 15000}, {"date": "2025-10-30", "owner": "", "symbol": "EXC", "asset": "Charles Schwab Brokerage Account 924 SP Exelon Corporation", "side": "BUY", "lo": 1001, "hi": 15000}, {"date": "2025-10-31", "owner": "", "symbol": "FN", "asset": "Charles Schwab 401K > Schwab 893 SP Fabrinet Ordinary Shares", "side": "SELL", "lo": 1001, "hi": 15000}, {"date": "2025-10-30", "owner": "", "symbol": "FN", "asset": "Fabrinet Ordinary Shares", "side": "SELL", "lo": 1001, "hi": 15000}, {"date": "2025-10-30", "owner": "", "symbol": "FN", "asset": "Charles Schwab Brokerage Account 924 SP Fabrinet Ordinary Shares", "side": "BUY", "lo": 1001, "hi": 15000}, {"date": "2025-10-30", "owner": "", "symbol": "IT", "asset": "Charles Schwab Brokerage Account 924 SP Gartner, Inc. Common Stock", "side": "SELL", "lo": 1001, "hi": 15000}, {"date": "2025-10-30", "owner": "", "symbol": "IT", "asset": "Charles Schwab Brokerage Account 924 SP Gartner, Inc. Common Stock", "side": "BUY", "lo": 1001, "hi": 15000}, {"date": "2025-10-31", "owner": "", "symbol": "IT", "asset": "Charles Schwab 401K > Schwab 893 SP Gartner, Inc. Common Stock", "side": "SELL", "lo": 1001, "hi": 15000}, {"date": "2025-10-30", "owner": "", "symbol": "GS", "asset": "Charles Schwab Brokerage Account 924 SP Goldman Sachs Group, Inc.", "side": "SELL", "lo": 1001, "hi": 15000}, {"date": "2025-10-30", "owner": "", "symbol": "GS", "asset": "Charles Schwab Brokerage Account 924 SP Goldman Sachs Group, Inc.", "side": "BUY", "lo": 1001, "hi": 15000}, {"date": "2025-10-31", "owner": "", "symbol": "GS", "asset": "Charles Schwab 401K > Schwab 893 SP Goldman Sachs Group, Inc.", "side": "SELL", "lo": 1001, "hi": 15000}, {"date": "2025-10-30", "owner": "", "symbol": "ITT", "asset": "Charles Schwab Brokerage Account 924 SP ITT Inc. Common Stock", "side": "SELL", "lo": 1001, "hi": 15000}, {"date": "2025-10-30", "owner": "", "symbol": "ITT", "asset": "Charles Schwab Brokerage Account 924 SP ITT Inc. Common Stock", "side": "BUY", "lo": 1001, "hi": 15000}, {"date": "2025-10-31", "owner": "", "symbol": "ITT", "asset": "Charles Schwab 401K > Schwab 893 SP ITT Inc. Common Stock", "side": "SELL", "lo": 1001, "hi": 15000}, {"date": "2025-10-31", "owner": "", "symbol": "OSK", "asset": "Oshkosh Corporation", "side": "SELL", "lo": 1001, "hi": 15000}, {"date": "2025-10-30", "owner": "", "symbol": "OSK", "asset": "Charles Schwab 401K > Schwab 893 SP Oshkosh Corporation", "side": "BUY", "lo": 1001, "hi": 15000}, {"date": "2025-10-30", "owner": "", "symbol": "OSK", "asset": "Charles Schwab 401K > Schwab 893 SP Oshkosh Corporation", "side": "SELL", "lo": 1001, "hi": 15000}, {"date": "2025-10-31", "owner": "", "symbol": "PEP", "asset": "Charles Schwab 401K > Schwab 893 SP Pepsico, Inc.", "side": "SELL", "lo": 1001, "hi": 15000}, {"date": "2025-10-30", "owner": "", "symbol": "PEP", "asset": "Charles Schwab 401K > Schwab 893 SP Pepsico, Inc.", "side": "BUY", "lo": 1001, "hi": 15000}, {"date": "2025-10-30", "owner": "", "symbol": "PEP", "asset": "Charles Schwab 401K > Schwab 893 SP Pepsico, Inc.", "side": "SELL", "lo": 1001, "hi": 15000}, {"date": "2025-10-31", "owner": "", "symbol": "PII", "asset": "Charles Schwab 401K > Schwab 893 SP Polaris Inc. Common Stock", "side": "SELL", "lo": 1001, "hi": 15000}, {"date": "2025-10-30", "owner": "", "symbol": "PII", "asset": "Polaris Inc. Common Stock", "side": "BUY", "lo": 1001, "hi": 15000}, {"date": "2025-10-30", "owner": "", "symbol": "PII", "asset": "Charles Schwab 401K > Schwab 893 SP Polaris Inc. Common Stock", "side": "SELL", "lo": 1001, "hi": 15000}, {"date": "2025-10-31", "owner": "", "symbol": "SAP", "asset": "Charles Schwab 401K > Schwab 893 SP SAP SE ADS", "side": "SELL", "lo": 1001, "hi": 15000}, {"date": "2025-10-30", "owner": "", "symbol": "SAP", "asset": "Charles Schwab 401K > Schwab 893 SP SAP SE ADS", "side": "BUY", "lo": 1001, "hi": 15000}, {"date": "2025-10-30", "owner": "", "symbol": "SAP", "asset": "Charles Schwab 401K > Schwab 893 SP SAP SE ADS", "side": "SELL", "lo": 1001, "hi": 15000}, {"date": "2025-10-14", "owner": "", "symbol": "SAP", "asset": "Charles Schwab Brokerage Account 924 SP SAP SE ADS", "side": "SELL", "lo": 1001, "hi": 15000}, {"date": "2025-10-30", "owner": "", "symbol": "SR", "asset": "Charles Schwab Brokerage Account 924 SP Spire Inc. Common Stock", "side": "SELL", "lo": 1001, "hi": 15000}, {"date": "2025-10-30", "owner": "", "symbol": "SR", "asset": "Charles Schwab Brokerage Account 924 SP Spire Inc. Common Stock", "side": "BUY", "lo": 1001, "hi": 15000}, {"date": "2025-10-31", "owner": "", "symbol": "SR", "asset": "Charles Schwab 401K > Schwab 893 SP Spire Inc. Common Stock", "side": "SELL", "lo": 1001, "hi": 15000}, {"date": "2025-10-30", "owner": "", "symbol": "TER", "asset": "Charles Schwab Brokerage Account 924 SP Teradyne, Inc.", "side": "SELL", "lo": 1001, "hi": 15000}, {"date": "2025-10-30", "owner": "", "symbol": "TER", "asset": "Charles Schwab Brokerage Account 924 SP Teradyne, Inc.", "side": "BUY", "lo": 1001, "hi": 15000}, {"date": "2025-10-31", "owner": "", "symbol": "TER", "asset": "Charles Schwab 401K > Schwab 893 SP Teradyne, Inc.", "side": "SELL", "lo": 1001, "hi": 15000}, {"date": "2025-10-30", "owner": "", "symbol": "TMUS", "asset": "Charles Schwab 401K > Schwab 893 SP T-Mobile US, Inc.", "side": "BUY", "lo": 1001, "hi": 15000}, {"date": "2025-10-30", "owner": "", "symbol": "TMUS", "asset": "Charles Schwab 401K > Schwab 893 SP T-Mobile US, Inc.", "side": "SELL", "lo": 1001, "hi": 15000}, {"date": "2025-10-31", "owner": "", "symbol": "TMUS", "asset": "Charles Schwab Brokerage Account 924 SP T-Mobile US, Inc.", "side": "SELL", "lo": 1001, "hi": 15000}, {"date": "2025-10-30", "owner": "", "symbol": "V", "asset": "Charles Schwab 401K > Schwab 893 SP Visa Inc.", "side": "BUY", "lo": 1001, "hi": 15000}, {"date": "2025-10-30", "owner": "", "symbol": "V", "asset": "Charles Schwab 401K > Schwab 893 SP Visa Inc.", "side": "SELL", "lo": 1001, "hi": 15000}, {"date": "2025-10-31", "owner": "", "symbol": "V", "asset": "Charles Schwab Brokerage Account 924 SP Visa Inc.", "side": "SELL", "lo": 1001, "hi": 15000}]}