{"Nifty 50": 25157.5, "Nifty Next 50": 66864.45, "Nifty 100": 25701.4, "Nifty 200": 13959.55, "Nifty 500": 22835.15, "Nifty Midcap 50": 16453.55, "NIFTY Midcap 100": 57423.65, "NIFTY Smallcap 100": 16551.2, "Nifty50 Dividend Points": 264.68, "Nifty Auto": 26871.25, "Nifty Bank": 58800.3, "Nifty Energy": 33370.05, "Nifty Financial Services": 26963.5, "Nifty FMCG": 51402.5, "Nifty IT": 37992.3, "Nifty Media": 1354.0, "Nifty Metal": 11438.95, "Nifty MNC": 29925.0, "Nifty Pharma": 21584.4, "Nifty PSU Bank": 8779.4, "Nifty Realty": 788.3, "Nifty India Consumption": 11662.0, "Nifty Commodities": 9347.5, "Nifty Dividend Opportunities 50": 6282.25, "Nifty Infrastructure": 9015.5, "Nifty PSE": 9620.35, "Nifty Services Sector": 32910.65, "Nifty50 Shariah": 4778.6, "Nifty500 Shariah": 6907.1, "Nifty Low Volatility 50": 24887.3, "Nifty Alpha 50": 47996.45, "Nifty High Beta 50": 3724.6, "Nifty100 Equal Weight": 32800.65, "Nifty100 Liquid 15": 7282.7, "Nifty CPSE": 6367.15, "Nifty50 Value 20": 13058.95, "Nifty Midcap Liquid 15": 15300.6, "Nifty Shariah 25": 8230.0, "India VIX": 13.78, "Nifty Growth Sectors 15": 12170.1, "Nifty50 TR 1x Inverse": 170.3, "Nifty50 TR 2x Leverage": 20343.7, "Nifty50 PR 1x Inverse": 208.3, "Nifty50 PR 2x Leverage": 13579.05, "NIFTY100 Quality 30": 5718.4, "Nifty India Corporate Group Index - Mahindra Group": 38698.53, "Nifty India Corporate Group Index - Tata Group": 15712.42, "Nifty India Corporate Group Index - Aditya Birla Group": 9056.77, "Nifty Conglomerate 50": 14351.67, "Nifty India Infrastructure & Logistics": 10693.45, "Nifty India FPI 150": 1556.45, "Nifty Waves": 1922.85, "Nifty500 Healthcare": 17739.25, "Nifty India Corporate Group Index - Tata Group 25% Cap": 14755.9, "Nifty Private Bank": 28162.65, "Nifty Smallcap 250": 15478.8, "Nifty Smallcap 50": 8085.55, "Nifty Midcap 150": 21118.45, "Nifty Midcap Select": 13155.05, "NIFTY LargeMidcap 250": 16104.7, "NIFTY SME EMERGE": 12860.2, "Nifty Oil & Gas": 11402.7, "Nifty Financial Services 25/50": 29439.95, "Nifty Healthcare Index": 13910.3, "Nifty500 Multicap 50:25:25": 15667.75, "Nifty Microcap 250": 20653.1, "Nifty Total Market": 12792.45, "Nifty India Digital": 9140.05, "Nifty Mobility": 21980.9, "Nifty India Defence": 7461.05, "Nifty Financial Services Ex-Bank": 30770.45, "Nifty Housing": 11358.95, "Nifty Transportation & Logistics": 24680.9, "Nifty MidSmall Financial Services": 20372.8, "Nifty MidSmall Healthcare": 41714.35, "Nifty MidSmall IT & Telecom": 9812.9, "Nifty MidSmall India Consumption": 17547.3, "Nifty REITs & InvITs": 1359.42, "Nifty Core Housing": 14810.3, "Nifty500 Multicap Infrastructure 50:30:20": 13419.3, "Nifty Rural": 15556.7, "Nifty Capital Markets": 4512.5, "Nifty India New Age Consumption": 11132.95, "Nifty India Select 5 Corporate Groups (MAATR)": 37303.45, "Nifty India Railways PSU": 3235.98, "Nifty Consumer Durables": 34740.0, "Nifty Non-Cyclical Consumer": 15195.75, "Nifty500 Multicap India Manufacturing 50:30:20": 15035.15, "Nifty EV & New Age Automotive": 2945.6, "Nifty500 LargeMidSmall Equal-Cap Weighted": 17114.55, "Nifty India Tourism": 7809.45, "Nifty MidSmallcap 400": 19025.6, "Nifty IPO": 1910.0, "Nifty India Internet": 1333.0, "Nifty Chemicals": 27059.85, "Nifty100 Low Volatility 30": 20424.9, "NIFTY Quality Low-Volatility 30": 16980.65, "NIFTY Alpha Quality Low-Volatility 30": 22043.5, "NIFTY Alpha Quality Value Low-Volatility 30": 20676.3, "NIFTY200 Quality 30": 20814.1, "NIFTY Midcap150 Quality 50": 22910.3, "Nifty200 Momentum 30": 30350.95, "Nifty India Manufacturing": 14759.85, "Nifty100 ESG Sector Leaders": 4213.85, "Nifty200 Alpha 30": 24171.7, "Nifty Midcap150 Momentum 50": 59214.75, "Nifty Smallcap250 Quality 50": 23965.5, "Nifty Smallcap250 Momentum Quality 100": 41254.35, "Nifty MidSmallcap400 Momentum Quality 100": 45564.65, "Nifty500 Momentum 50": 50664.35, "Nifty200 Value 30": 14685.5, "Nifty Top 10 Equal Weight": 9513.2, "Nifty500 Multicap Momentum Quality 50": 39759.0, "Nifty Top 15 Equal Weight": 10604.7, "Nifty Top 20 Equal Weight": 9353.45, "Nifty500 Quality 50": 18030.15, "Nifty500 Low Volatility 50": 22351.65, "NIFTY100 ESG": 5053.7, "NIFTY100 Enhanced ESG": 5095.5, "NIFTY500 Value 50": 15408.45, "NIFTY100 Alpha 30": 17568.45, "Nifty500 Multifactor MQVLv 50": 30747.05, "NIFTY Alpha Low-Volatility 30": 26366.65, "Nifty500 Flexicap Quality 30": 10359.0, "Nifty Total Market Momentum Quality 50": 40206.4, "Nifty500 Equal Weight": 13364.5, "NIFTY50 Equal Weight": 32386.3, "Nifty 50 Futures Index": 6384.49, "Nifty 50 Arbitrage": 2619.75, "Nifty 50 Futures TR Index": 26922.26, "Nifty 8-13 yr G-Sec": 2968.44, "Nifty 4-8 yr G-Sec Index": 3220.58, "Nifty 11-15 yr G-Sec Index": 3228.45, "Nifty 15 yr and above G-Sec Index": 3454.82, "Nifty Composite G-sec Index": 3043.58, "Nifty 10 yr Benchmark G-Sec": 2612.98, "Nifty 10 yr Benchmark G-Sec (Clean Price)": 888.43, "Nifty BHARAT Bond Index - April 2030": 1555.62, "Nifty BHARAT Bond Index - April 2031": 1414.39, "Nifty BHARAT Bond Index - April 2032": 1284.57, "Nifty BHARAT Bond Index - April 2033": 1247.87, "Nifty 1D Rate Index": 2518.58, "Nifty50 USD": 9505.82}