{"Nifty 50": 22331.4, "Nifty Next 50": 60349.8, "Nifty 100": 22875.5, "Nifty 200": 12492.1, "Nifty 500": 20528.05, "Nifty Midcap 50": 14983.35, "NIFTY Midcap 100": 52650.0, "NIFTY Smallcap 100": 15203.8, "Nifty50 Dividend Points": 279.19, "Nifty Auto": 23769.6, "Nifty Bank": 50275.35, "Nifty Energy": 34849.7, "Nifty Financial Services": 23521.8, "Nifty FMCG": 45538.65, "Nifty IT": 29062.6, "Nifty Media": 1261.85, "Nifty Metal": 11138.4, "Nifty MNC": 27791.25, "Nifty Pharma": 22232.25, "Nifty PSU Bank": 7873.45, "Nifty Realty": 651.15, "Nifty India Consumption": 10334.35, "Nifty Commodities": 9127.75, "Nifty Dividend Opportunities 50": 5644.3, "Nifty Infrastructure": 8560.95, "Nifty PSE": 9559.0, "Nifty Services Sector": 28363.6, "Nifty50 Shariah": 4118.8, "Nifty500 Shariah": 6215.15, "Nifty Low Volatility 50": 22582.0, "Nifty Alpha 50": 44487.95, "Nifty High Beta 50": 3317.65, "Nifty100 Equal Weight": 29787.2, "Nifty100 Liquid 15": 6586.95, "Nifty CPSE": 6900.85, "Nifty50 Value 20": 11586.0, "Nifty Midcap Liquid 15": 13726.45, "Nifty Shariah 25": 7255.85, "India VIX": 27.89, "Nifty Growth Sectors 15": 10408.35, "Nifty50 TR 1x Inverse": 192.1, "Nifty50 TR 2x Leverage": 15775.15, "Nifty50 PR 1x Inverse": 235.0, "Nifty50 PR 2x Leverage": 10517.7, "NIFTY100 Quality 30": 5033.1, "Nifty200 Momentum 30": 27071.65, "Nifty India Manufacturing": 14032.55, "Nifty100 ESG Sector Leaders": 3707.2, "Nifty200 Alpha 30": 22065.75, "Nifty Midcap150 Momentum 50": 54460.9, "Nifty Smallcap250 Quality 50": 21675.8, "Nifty Smallcap250 Momentum Quality 100": 37605.15, "Nifty MidSmallcap400 Momentum Quality 100": 42723.25, "Nifty500 Momentum 50": 45987.05, "Nifty200 Value 30": 14041.3, "Nifty Top 10 Equal Weight": 8195.7, "Nifty500 Multicap Momentum Quality 50": 36407.1, "Nifty Top 15 Equal Weight": 9129.2, "Nifty Top 20 Equal Weight": 8160.7, "Nifty500 Quality 50": 16709.15, "Nifty500 Low Volatility 50": 20579.9, "NIFTY100 ESG": 4444.8, "NIFTY100 Enhanced ESG": 4477.1, "NIFTY500 Value 50": 14937.7, "NIFTY100 Alpha 30": 15765.85, "Nifty500 Multifactor MQVLv 50": 28459.05, "NIFTY Alpha Low-Volatility 30": 23961.3, "Nifty500 Flexicap Quality 30": 8924.15, "NIFTY50 Equal Weight": 29556.95, "Nifty500 Equal Weight": 12226.1, "Nifty 50 Futures Index": 5589.46, "Nifty 50 Arbitrage": 2657.26, "Nifty 50 Futures TR Index": 23849.59, "Nifty India Corporate Group Index - Mahindra Group": 32165.37, "Nifty India Corporate Group Index - Aditya Birla Group": 8115.07, "Nifty India Corporate Group Index - Tata Group": 13416.5, "Nifty India Corporate Group Index - Tata Group 25% Cap": 13255.55, "Nifty Private Bank": 24144.85, "Nifty Smallcap 250": 14288.45, "Nifty Smallcap 50": 7465.05, "Nifty Midcap 150": 19430.9, "Nifty Midcap Select": 12158.75, "NIFTY LargeMidcap 250": 14574.5, "NIFTY SME EMERGE": 11025.8, "Nifty Oil & Gas": 10788.05, "Nifty Financial Services 25/50": 25705.6, "Nifty Healthcare Index": 14201.05, "Nifty500 Multicap 50:25:25": 14189.1, "Nifty Microcap 250": 18892.95, "Nifty Total Market": 11507.05, "Nifty India Digital": 7268.6, "Nifty Mobility": 19388.85, "Nifty India Defence": 7214.3, "Nifty Financial Services Ex-Bank": 27011.2, "Nifty Housing": 10501.6, "Nifty Transportation & Logistics": 21520.0, "Nifty MidSmall Financial Services": 18073.8, "Nifty MidSmall Healthcare": 41705.75, "Nifty MidSmall IT & Telecom": 7779.1, "Nifty MidSmall India Consumption": 15848.5, "Nifty REITs & InvITs": 1308.87, "Nifty Core Housing": 12986.1, "Nifty500 Multicap Infrastructure 50:30:20": 12696.1, "Nifty Rural": 13918.35, "Nifty Capital Markets": 4251.8, "Nifty India New Age Consumption": 9703.55, "Nifty India Select 5 Corporate Groups (MAATR)": 33378.9, "Nifty India Railways PSU": 2748.95, "Nifty Consumer Durables": 33023.3, "Nifty Non-Cyclical Consumer": 13339.65, "Nifty500 Multicap India Manufacturing 50:30:20": 14359.1, "Nifty EV & New Age Automotive": 2631.45, "Nifty500 LargeMidSmall Equal-Cap Weighted": 15589.65, "Nifty India Tourism": 6517.65, "Nifty MidSmallcap 400": 17524.35, "Nifty IPO": 1782.65, "Nifty India Internet": 1075.85, "Nifty Chemicals": 24936.0, "Nifty Conglomerate 50": 12787.65, "Nifty India Infrastructure & Logistics": 10191.85, "Nifty India FPI 150": 1401.15, "Nifty Waves": 1582.65, "Nifty Smallcap 500": 15971.9, "Nifty Cement": 13767.34, "Nifty REITs & Realty": 1632.57, "Nifty500 Healthcare": 17882.2, "Nifty MidSmallcap400 50:50": 16900.67, "Nifty Total Market Momentum Quality 50": 37787.95, "Nifty100 Low Volatility 30": 18308.4, "NIFTY Quality Low-Volatility 30": 15088.65, "NIFTY Alpha Quality Low-Volatility 30": 20283.75, "NIFTY Alpha Quality Value Low-Volatility 30": 18543.9, "NIFTY200 Quality 30": 18207.0, "NIFTY Midcap150 Quality 50": 20728.25, "Nifty 8-13 yr G-Sec": 2940.64, "Nifty 4-8 yr G-Sec Index": 3207.66, "Nifty 11-15 yr G-Sec Index": 3190.78, "Nifty 15 yr and above G-Sec Index": 3356.28, "Nifty Composite G-sec Index": 3009.05, "Nifty 10 yr Benchmark G-Sec": 2581.47, "Nifty 10 yr Benchmark G-Sec (Clean Price)": 866.49, "Nifty BHARAT Bond Index - April 2030": 1564.17, "Nifty BHARAT Bond Index - April 2031": 1419.43, "Nifty BHARAT Bond Index - April 2032": 1288.32, "Nifty BHARAT Bond Index - April 2033": 1249.29, "Nifty 1D Rate Index": 2541.9, "Nifty50 USD": 8158.08}