{"Nifty 50": 24363.3, "Nifty Next 50": 65514.7, "Nifty 100": 24934.05, "Nifty 200": 13555.15, "Nifty 500": 22443.15, "Nifty Midcap 50": 15785.6, "NIFTY Midcap 100": 56002.2, "NIFTY Smallcap 100": 17428.2, "Nifty50 Dividend Points": 174.84, "Nifty Auto": 23474.65, "Nifty Bank": 55004.9, "Nifty Energy": 34391.95, "Nifty Financial Services": 26167.35, "Nifty FMCG": 54900.95, "Nifty IT": 34398.5, "Nifty Media": 1635.1, "Nifty Metal": 9147.1, "Nifty MNC": 28134.05, "Nifty Pharma": 21402.15, "Nifty PSU Bank": 6881.25, "Nifty Realty": 874.15, "Nifty India Consumption": 11647.1, "Nifty Commodities": 8638.9, "Nifty Dividend Opportunities 50": 5806.85, "Nifty Infrastructure": 8879.1, "Nifty PSE": 9529.4, "Nifty Services Sector": 32033.2, "Nifty50 Shariah": 4508.8, "Nifty500 Shariah": 6865.95, "Nifty Low Volatility 50": 24298.4, "Nifty Alpha 50": 49661.7, "Nifty High Beta 50": 3533.85, "Nifty100 Equal Weight": 31741.1, "Nifty100 Liquid 15": 6772.25, "Nifty CPSE": 6317.2, "Nifty50 Value 20": 12307.45, "Nifty Midcap Liquid 15": 14644.7, "Nifty Shariah 25": 7994.2, "India VIX": 12.03, "Nifty Growth Sectors 15": 11148.7, "Nifty50 TR 1x Inverse": 172.75, "Nifty50 TR 2x Leverage": 19466.65, "Nifty50 PR 1x Inverse": 210.5, "Nifty50 PR 2x Leverage": 13086.25, "NIFTY100 Quality 30": 5431.05, "Nifty India Corporate Group Index - Mahindra Group": 33985.25, "Nifty India Corporate Group Index - Tata Group": 15425.23, "Nifty India Corporate Group Index - Aditya Birla Group": 8055.77, "Nifty India Infrastructure & Logistics": 11075.69, "Nifty Waves": 2120.08, "Nifty500 Healthcare": 18464.57, "Nifty India Corporate Group Index - Tata Group 25% Cap": 14486.15, "Nifty Private Bank": 26564.7, "Nifty Smallcap 250": 16541.9, "Nifty Smallcap 50": 8416.2, "Nifty Midcap 150": 20848.25, "Nifty Midcap Select": 12506.3, "NIFTY LargeMidcap 250": 15760.3, "NIFTY SME EMERGE": 14813.9, "Nifty Oil & Gas": 10989.15, "Nifty Financial Services 25/50": 28106.45, "Nifty Healthcare Index": 14135.55, "Nifty500 Multicap 50:25:25": 15632.45, "Nifty Microcap 250": 23072.85, "Nifty Total Market": 12632.35, "Nifty India Digital": 8641.35, "Nifty Mobility": 20582.7, "Nifty India Defence": 7607.9, "Nifty Financial Services Ex-Bank": 28868.75, "Nifty Housing": 11253.6, "Nifty Transportation & Logistics": 23106.0, "Nifty MidSmall Financial Services": 17735.95, "Nifty MidSmall Healthcare": 43592.4, "Nifty MidSmall IT & Telecom": 9215.4, "Nifty MidSmall India Consumption": 19121.7, "Nifty REITs & InvITs": 1234.5, "Nifty Core Housing": 15794.85, "Nifty500 Multicap Infrastructure 50:30:20": 13640.45, "Nifty Rural": 14660.8, "Nifty Capital Markets": 4318.5, "Nifty India New Age Consumption": 11420.25, "Nifty India Select 5 Corporate Groups (MAATR)": 35087.35, "Nifty India Railways PSU": 3467.9, "Nifty Consumer Durables": 37549.6, "Nifty Non-Cyclical Consumer": 15938.4, "Nifty500 Multicap India Manufacturing 50:30:20": 14659.65, "Nifty EV & New Age Automotive": 2853.1, "Nifty500 LargeMidSmall Equal-Cap Weighted": 17238.05, "Nifty India Tourism": 8939.2, "Nifty MidSmallcap 400": 19305.75, "Nifty IPO": 2044.9, "Nifty India Internet": 1366.5, "Nifty Chemicals": 29982.61, "Nifty100 Low Volatility 30": 19660.8, "NIFTY Quality Low-Volatility 30": 16645.75, "NIFTY Alpha Quality Low-Volatility 30": 21662.05, "NIFTY Alpha Quality Value Low-Volatility 30": 20014.55, "NIFTY200 Quality 30": 20075.65, "NIFTY Midcap150 Quality 50": 23691.2, "Nifty200 Momentum 30": 29703.3, "Nifty India Manufacturing": 13947.25, "Nifty100 ESG Sector Leaders": 4076.45, "Nifty200 Alpha 30": 24195.05, "Nifty Midcap150 Momentum 50": 59780.0, "Nifty Smallcap250 Quality 50": 26469.75, "Nifty Smallcap250 Momentum Quality 100": 44249.05, "Nifty MidSmallcap400 Momentum Quality 100": 47270.0, "Nifty500 Momentum 50": 50603.1, "Nifty200 Value 30": 12652.1, "Nifty Top 10 Equal Weight": 9286.65, "Nifty500 Multicap Momentum Quality 50": 40116.75, "Nifty Top 15 Equal Weight": 9964.7, "Nifty Top 20 Equal Weight": 8849.85, "Nifty500 Quality 50": 18678.9, "Nifty500 Low Volatility 50": 21014.65, "NIFTY100 ESG": 4794.5, "NIFTY100 Enhanced ESG": 4829.65, "NIFTY500 Value 50": 13663.65, "NIFTY100 Alpha 30": 17815.6, "Nifty500 Multifactor MQVLv 50": 29868.85, "NIFTY Alpha Low-Volatility 30": 25823.8, "Nifty500 Flexicap Quality 30": 10201.64, "Nifty Total Market Momentum Quality 50": 41566.25, "Nifty500 Equal Weight": 13829.8, "NIFTY50 Equal Weight": 30613.45, "Nifty 50 Futures Index": 6388.95, "Nifty 50 Arbitrage": 2534.91, "Nifty 50 Futures TR Index": 26223.76, "Nifty 8-13 yr G-Sec": 2931.04, "Nifty 4-8 yr G-Sec Index": 3174.18, "Nifty 11-15 yr G-Sec Index": 3209.78, "Nifty 15 yr and above G-Sec Index": 3467.65, "Nifty Composite G-sec Index": 3017.34, "Nifty 10 yr Benchmark G-Sec": 2598.26, "Nifty 10 yr Benchmark G-Sec (Clean Price)": 909.6, "Nifty BHARAT Bond Index - April 2030": 1540.05, "Nifty BHARAT Bond Index - April 2031": 1405.35, "Nifty BHARAT Bond Index - April 2032": 1281.0, "Nifty BHARAT Bond Index - April 2033": 1244.44, "Nifty 1D Rate Index": 2458.53, "Nifty50 USD": 9630.11}